Metadata-Version: 1.0
Name: distributions-GB-JF
Version: 0.1
Summary: Gaussian and Binomial distributions
Home-page: UNKNOWN
Author: Junmei Fan
Author-email: biofjm@gmail.com
License: UNKNOWN
Platform: UNKNOWN
